{
  "index": {
    "links": {
      "/": [
        {
          "source": "/",
          "target": "/tags/gamedev",
          "text": "Game Development"
        },
        {
          "source": "/",
          "target": "/tags/math",
          "text": "Math"
        }
      ],
      "/GameDev/Frame": [
        {
          "source": "/GameDev/Frame",
          "target": "/GameDev/FPS",
          "text": "FPS"
        }
      ],
      "/GameDev/Game-Loop": [
        {
          "source": "/GameDev/Game-Loop",
          "target": "/Game-Engine",
          "text": "game engine"
        },
        {
          "source": "/GameDev/Game-Loop",
          "target": "/GameDev/Frame",
          "text": "frames"
        }
      ],
      "/GameDev/Game-Physics": [
        {
          "source": "/GameDev/Game-Physics",
          "target": "/GameDev/Vector",
          "text": "Vector"
        },
        {
          "source": "/GameDev/Game-Physics",
          "target": "/GameDev/Kinematics",
          "text": "Kinematics"
        },
        {
          "source": "/GameDev/Game-Physics",
          "target": "/GameDev/Game-Loop",
          "text": "Game Loop"
        },
        {
          "source": "/GameDev/Game-Physics",
          "target": "/GameDev/Game-Loop",
          "text": "Fixed Time-step"
        },
        {
          "source": "/GameDev/Game-Physics",
          "target": "/GameDev/Frame",
          "text": "Frame"
        },
        {
          "source": "/GameDev/Game-Physics",
          "target": "/GameDev/Game-Loop",
          "text": "Variable Time-step"
        }
      ],
      "/GameDev/Scalar": [
        {
          "source": "/GameDev/Scalar",
          "target": "/GameDev/magnitude",
          "text": "magnitude"
        },
        {
          "source": "/GameDev/Scalar",
          "target": "/GameDev/Vector",
          "text": "Vector"
        }
      ],
      "/GameDev/Vector": [
        {
          "source": "/GameDev/Vector",
          "target": "/GameDev/magnitude",
          "text": "magnitude"
        },
        {
          "source": "/GameDev/Vector",
          "target": "/GameDev/Scalar",
          "text": "Scalar"
        },
        {
          "source": "/GameDev/Vector",
          "target": "/GameDev/Kinematics",
          "text": "reflection angle"
        },
        {
          "source": "/GameDev/Vector",
          "target": "/GameDev/2D-Space",
          "text": "GameDev/2D Space"
        }
      ],
      "/Hacking/Port-Enumeration/Port-111-RPC-NFS": [
        {
          "source": "/Hacking/Port-Enumeration/Port-111-RPC-NFS",
          "target": "/Hacking/Port",
          "text": "Port"
        }
      ],
      "/Hacking/Port-Enumeration/Port-139-445-SMB-NetBios": [
        {
          "source": "/Hacking/Port-Enumeration/Port-139-445-SMB-NetBios",
          "target": "/Hacking/Port",
          "text": "Ports"
        }
      ],
      "/Hacking/Port-Enumeration/Port-161-SNMP": [
        {
          "source": "/Hacking/Port-Enumeration/Port-161-SNMP",
          "target": "/Hacking/Port",
          "text": "Port"
        }
      ],
      "/Hacking/Port-Enumeration/Port-25-SMTP": [
        {
          "source": "/Hacking/Port-Enumeration/Port-25-SMTP",
          "target": "/Hacking/Port",
          "text": "port"
        }
      ],
      "/Hacking/Port-Enumeration/Port-80-443-HTTPS": [
        {
          "source": "/Hacking/Port-Enumeration/Port-80-443-HTTPS",
          "target": "/Hacking/Port",
          "text": "Ports"
        }
      ],
      "/Hacking/Port-Scanning": [
        {
          "source": "/Hacking/Port-Scanning",
          "target": "/TCP-Handshake",
          "text": "TCP Handshake"
        },
        {
          "source": "/Hacking/Port-Scanning",
          "target": "/UDP-protocol",
          "text": "UDP protocol"
        }
      ],
      "/Oscp-experience": [
        {
          "source": "/Oscp-experience",
          "target": "/Hacking/Cyber-Security-Basic-Terms-and-Concepts",
          "text": "terms and concepts"
        },
        {
          "source": "/Oscp-experience",
          "target": "/Hacking/AD/Active-Directory",
          "text": "Active Directory"
        },
        {
          "source": "/Oscp-experience",
          "target": "/Hacking/Port-Scanning",
          "text": "Port Scanning"
        },
        {
          "source": "/Oscp-experience",
          "target": "/Hacking/Port",
          "text": "port"
        },
        {
          "source": "/Oscp-experience",
          "target": "/Hacking/Cyber-Security-Basic-Terms-and-Concepts",
          "text": "penetration testing methodology"
        },
        {
          "source": "/Oscp-experience",
          "target": "/Hacking/Cyber-Security-Basic-Terms-and-Concepts",
          "text": "remote code execution"
        },
        {
          "source": "/Oscp-experience",
          "target": "/Hacking/reverse-shell",
          "text": "reverse shell"
        }
      ]
    },
    "backlinks": {
      "/Game-Engine": [
        {
          "source": "/GameDev/Game-Loop",
          "target": "/Game-Engine",
          "text": "game engine"
        }
      ],
      "/GameDev/2D-Space": [
        {
          "source": "/GameDev/Vector",
          "target": "/GameDev/2D-Space",
          "text": "GameDev/2D Space"
        }
      ],
      "/GameDev/FPS": [
        {
          "source": "/GameDev/Frame",
          "target": "/GameDev/FPS",
          "text": "FPS"
        }
      ],
      "/GameDev/Frame": [
        {
          "source": "/GameDev/Game-Loop",
          "target": "/GameDev/Frame",
          "text": "frames"
        },
        {
          "source": "/GameDev/Game-Physics",
          "target": "/GameDev/Frame",
          "text": "Frame"
        }
      ],
      "/GameDev/Game-Loop": [
        {
          "source": "/GameDev/Game-Physics",
          "target": "/GameDev/Game-Loop",
          "text": "Game Loop"
        },
        {
          "source": "/GameDev/Game-Physics",
          "target": "/GameDev/Game-Loop",
          "text": "Fixed Time-step"
        },
        {
          "source": "/GameDev/Game-Physics",
          "target": "/GameDev/Game-Loop",
          "text": "Variable Time-step"
        }
      ],
      "/GameDev/Kinematics": [
        {
          "source": "/GameDev/Game-Physics",
          "target": "/GameDev/Kinematics",
          "text": "Kinematics"
        },
        {
          "source": "/GameDev/Vector",
          "target": "/GameDev/Kinematics",
          "text": "reflection angle"
        }
      ],
      "/GameDev/Scalar": [
        {
          "source": "/GameDev/Vector",
          "target": "/GameDev/Scalar",
          "text": "Scalar"
        }
      ],
      "/GameDev/Vector": [
        {
          "source": "/GameDev/Game-Physics",
          "target": "/GameDev/Vector",
          "text": "Vector"
        },
        {
          "source": "/GameDev/Scalar",
          "target": "/GameDev/Vector",
          "text": "Vector"
        }
      ],
      "/GameDev/magnitude": [
        {
          "source": "/GameDev/Scalar",
          "target": "/GameDev/magnitude",
          "text": "magnitude"
        },
        {
          "source": "/GameDev/Vector",
          "target": "/GameDev/magnitude",
          "text": "magnitude"
        }
      ],
      "/Hacking/AD/Active-Directory": [
        {
          "source": "/Oscp-experience",
          "target": "/Hacking/AD/Active-Directory",
          "text": "Active Directory"
        }
      ],
      "/Hacking/Cyber-Security-Basic-Terms-and-Concepts": [
        {
          "source": "/Oscp-experience",
          "target": "/Hacking/Cyber-Security-Basic-Terms-and-Concepts",
          "text": "terms and concepts"
        },
        {
          "source": "/Oscp-experience",
          "target": "/Hacking/Cyber-Security-Basic-Terms-and-Concepts",
          "text": "penetration testing methodology"
        },
        {
          "source": "/Oscp-experience",
          "target": "/Hacking/Cyber-Security-Basic-Terms-and-Concepts",
          "text": "remote code execution"
        }
      ],
      "/Hacking/Port": [
        {
          "source": "/Hacking/Port-Enumeration/Port-111-RPC-NFS",
          "target": "/Hacking/Port",
          "text": "Port"
        },
        {
          "source": "/Hacking/Port-Enumeration/Port-139-445-SMB-NetBios",
          "target": "/Hacking/Port",
          "text": "Ports"
        },
        {
          "source": "/Hacking/Port-Enumeration/Port-161-SNMP",
          "target": "/Hacking/Port",
          "text": "Port"
        },
        {
          "source": "/Hacking/Port-Enumeration/Port-25-SMTP",
          "target": "/Hacking/Port",
          "text": "port"
        },
        {
          "source": "/Hacking/Port-Enumeration/Port-80-443-HTTPS",
          "target": "/Hacking/Port",
          "text": "Ports"
        },
        {
          "source": "/Oscp-experience",
          "target": "/Hacking/Port",
          "text": "port"
        }
      ],
      "/Hacking/Port-Scanning": [
        {
          "source": "/Oscp-experience",
          "target": "/Hacking/Port-Scanning",
          "text": "Port Scanning"
        }
      ],
      "/Hacking/reverse-shell": [
        {
          "source": "/Oscp-experience",
          "target": "/Hacking/reverse-shell",
          "text": "reverse shell"
        }
      ],
      "/TCP-Handshake": [
        {
          "source": "/Hacking/Port-Scanning",
          "target": "/TCP-Handshake",
          "text": "TCP Handshake"
        }
      ],
      "/UDP-protocol": [
        {
          "source": "/Hacking/Port-Scanning",
          "target": "/UDP-protocol",
          "text": "UDP protocol"
        }
      ],
      "/tags/gamedev": [
        {
          "source": "/",
          "target": "/tags/gamedev",
          "text": "Game Development"
        }
      ],
      "/tags/math": [
        {
          "source": "/",
          "target": "/tags/math",
          "text": "Math"
        }
      ]
    }
  },
  "links": [
    {
      "source": "/GameDev/Frame",
      "target": "/GameDev/FPS",
      "text": "FPS"
    },
    {
      "source": "/GameDev/Game-Loop",
      "target": "/Game-Engine",
      "text": "game engine"
    },
    {
      "source": "/GameDev/Game-Loop",
      "target": "/GameDev/Frame",
      "text": "frames"
    },
    {
      "source": "/GameDev/Game-Physics",
      "target": "/GameDev/Vector",
      "text": "Vector"
    },
    {
      "source": "/GameDev/Game-Physics",
      "target": "/GameDev/Kinematics",
      "text": "Kinematics"
    },
    {
      "source": "/GameDev/Game-Physics",
      "target": "/GameDev/Game-Loop",
      "text": "Game Loop"
    },
    {
      "source": "/GameDev/Game-Physics",
      "target": "/GameDev/Game-Loop",
      "text": "Fixed Time-step"
    },
    {
      "source": "/GameDev/Game-Physics",
      "target": "/GameDev/Frame",
      "text": "Frame"
    },
    {
      "source": "/GameDev/Game-Physics",
      "target": "/GameDev/Game-Loop",
      "text": "Variable Time-step"
    },
    {
      "source": "/GameDev/Scalar",
      "target": "/GameDev/magnitude",
      "text": "magnitude"
    },
    {
      "source": "/GameDev/Scalar",
      "target": "/GameDev/Vector",
      "text": "Vector"
    },
    {
      "source": "/GameDev/Vector",
      "target": "/GameDev/magnitude",
      "text": "magnitude"
    },
    {
      "source": "/GameDev/Vector",
      "target": "/GameDev/Scalar",
      "text": "Scalar"
    },
    {
      "source": "/GameDev/Vector",
      "target": "/GameDev/Kinematics",
      "text": "reflection angle"
    },
    {
      "source": "/GameDev/Vector",
      "target": "/GameDev/2D-Space",
      "text": "GameDev/2D Space"
    },
    {
      "source": "/Hacking/Port-Enumeration/Port-111-RPC-NFS",
      "target": "/Hacking/Port",
      "text": "Port"
    },
    {
      "source": "/Hacking/Port-Enumeration/Port-139-445-SMB-NetBios",
      "target": "/Hacking/Port",
      "text": "Ports"
    },
    {
      "source": "/Hacking/Port-Enumeration/Port-161-SNMP",
      "target": "/Hacking/Port",
      "text": "Port"
    },
    {
      "source": "/Hacking/Port-Enumeration/Port-25-SMTP",
      "target": "/Hacking/Port",
      "text": "port"
    },
    {
      "source": "/Hacking/Port-Enumeration/Port-80-443-HTTPS",
      "target": "/Hacking/Port",
      "text": "Ports"
    },
    {
      "source": "/Hacking/Port-Scanning",
      "target": "/TCP-Handshake",
      "text": "TCP Handshake"
    },
    {
      "source": "/Hacking/Port-Scanning",
      "target": "/UDP-protocol",
      "text": "UDP protocol"
    },
    {
      "source": "/Oscp-experience",
      "target": "/Hacking/Cyber-Security-Basic-Terms-and-Concepts",
      "text": "terms and concepts"
    },
    {
      "source": "/Oscp-experience",
      "target": "/Hacking/AD/Active-Directory",
      "text": "Active Directory"
    },
    {
      "source": "/Oscp-experience",
      "target": "/Hacking/Port-Scanning",
      "text": "Port Scanning"
    },
    {
      "source": "/Oscp-experience",
      "target": "/Hacking/Port",
      "text": "port"
    },
    {
      "source": "/Oscp-experience",
      "target": "/Hacking/Cyber-Security-Basic-Terms-and-Concepts",
      "text": "penetration testing methodology"
    },
    {
      "source": "/Oscp-experience",
      "target": "/Hacking/Cyber-Security-Basic-Terms-and-Concepts",
      "text": "remote code execution"
    },
    {
      "source": "/Oscp-experience",
      "target": "/Hacking/reverse-shell",
      "text": "reverse shell"
    },
    {
      "source": "/",
      "target": "/tags/gamedev",
      "text": "Game Development"
    },
    {
      "source": "/",
      "target": "/tags/math",
      "text": "Math"
    }
  ]
}